everbridge/__init__.py
everbridge/models.py
everbridge-0.2.1.dist-info/METADATA
everbridge-0.2.1.dist-info/WHEEL
everbridge-0.2.1.dist-info/RECORD
